deairequest/BacalhauProtocol.py
deairequest/DeProtocol.py
deairequest/DeProtocolSelector.py
deairequest/ErrorProtocol.py
deairequest/__init__.py
deairequest/amaksimov-python_data_science:latest.req
deairequest/docker_images.pv
deairequest/docker_images.pv.test
deairequest/logo.svg
deairequest/python:3.req
deairequest/pytorch-pytorch:2.0.1-cuda11.7-cudnn8-runtime.req
deairequest/sdk_data.py
deairequest/sdk_pandas.py
deairequest/sdk_tf.py
deairequest/sdk_torch.py
deairequest/tensorflow-tensorflow:latest-gpu-jupyter.req
deairequest/test.ipynb
deairequest/test.txt
deairequest/test2.ipynb
deairequest/test_DeAIRequest.py
deairequest/connectors/__init__.py
deairequest/connectors/bacalhau/__init__.py
deairequest/connectors/bacalhau/backends.py
deairequest/connectors/bacalhau/code.py
deairequest/connectors/bacalhau/deploy.py
deairequest/connectors/bacalhau/main.py
deairequest/connectors/bacalhau/mapping.py
deairequest/connectors/bacalhau/notebooks.py
deairequest/connectors/bacalhau/querybhl.py
deairequest/connectors/bacalhau/render.py
deairequest/connectors/bacalhau/stdlib.py
deairequest/connectors/bacalhau/step.py
deairequest-0.0.20.dist-info/LICENSE
deairequest-0.0.20.dist-info/METADATA
deairequest-0.0.20.dist-info/WHEEL
deairequest-0.0.20.dist-info/top_level.txt
deairequest-0.0.20.dist-info/zip-safe
deairequest-0.0.20.dist-info/RECORD
