Metadata-Version: 2.1
Name: deairequest
Version: 0.0.20
Summary: A Decentralised AI library which allows to run remote AI jobs
Author-email: Maarten Ectors <maarten@0011.ai>
Project-URL: Homepage, https://github.com/0011ai/deairequest
Project-URL: Bug Tracker, https://github.com/0011ai/deairequest/issues
Classifier: Programming Language :: Python :: 3
Classifier: License :: OSI Approved :: MIT License
Classifier: Operating System :: OS Independent
Requires-Python: >=3.7
License-File: LICENSE
